<!-- Requires: 2 hosts with at least one interface -->
<!-- ['machines'][2]['netconfig'][1]['addresses'][0] -->
<command_sequence>
    <command machine_id="1" type="exec" value="sleep 1"/>
    <command machine_id="2" type="exec" value="sleep 1"/>

    <command bg_id="1" machine_id="1" timeout="30" type="test" value="Multicast">
        <options>
            <option name="setup" value="send_simple"/>
            <option name="address" value="{$multicast_group}"/>
            <option name="port" value="{$port}"/>
            <option name="duration" value="{$test_duration}"/>
            <option name="delay" value="{$send_delay}"/>
            <option name="interface" value="{ip(1,1)}"/>
        </options>
    </command>

    <command machine_id="2" timeout="30" type="test" value="Multicast">
        <options>
            <option name="setup" value="recv_simple"/>
            <option name="address" value="{$multicast_group}"/>
            <option name="port" value="{$port}"/>
            <option name="duration" value="{$test_duration}"/>
            <option name="interface" value="{ip(2,1)}"/>

            <option name="condition" value="packets_received > 0"/>
        </options>
    </command>

    <command machine_id="1" type="wait" value="1"/>
</command_sequence>
